protonmail/__init__.py
protonmail/client.py
protonmail/constants.py
protonmail/exceptions.py
protonmail/logger.py
protonmail/models.py
protonmail/pgp.py
protonmail/utils/__init__.py
protonmail/utils/captcha_auto_solver_utils.py
protonmail/utils/pysrp.py
protonmail/utils/utils.py
protonmail_api_client-2.4.3.dist-info/licenses/LICENSE
protonmail_api_client-2.4.3.dist-info/METADATA
protonmail_api_client-2.4.3.dist-info/WHEEL
protonmail_api_client-2.4.3.dist-info/top_level.txt
protonmail_api_client-2.4.3.dist-info/RECORD
