Metadata-Version: 2.4
Name: protonmail-api-client
Version: 2.4.3
Summary: This is not an official python ProtonMail API client. it allows you to read, send and delete messages in protonmail, as well as render a ready-made template with embedded images.
Author-email: opulentfox-29 <3acqw2bx@duck.com>
License-Expression: GPL-3.0-or-later
Project-URL: Homepage, https://github.com/opulentfox-29/protonmail-api-client
Keywords: protonmail,api,client,proton,proton-mail,send,read,mail,email,python,python3
Requires-Python: >=3.9
License-File: LICENSE
Requires-Dist: PGPy13==0.6.1rc1
Requires-Dist: aiohttp
Requires-Dist: bcrypt
Requires-Dist: cryptography
Requires-Dist: numpy
Requires-Dist: opencv-python
Requires-Dist: pycryptodome
Requires-Dist: requests
Requires-Dist: requests-toolbelt
Requires-Dist: typing_extensions
Requires-Dist: tqdm
Provides-Extra: dev
Requires-Dist: setuptools>=77.0.0; extra == "dev"
Requires-Dist: build; extra == "dev"
Requires-Dist: twine; extra == "dev"
Dynamic: license-file
